bladoxy/LICENSE
bladoxy/README.md
bladoxy/__init__.py
bladoxy/requirements.txt
bladoxy/cli/__init__.py
bladoxy/cli/cli_app.py
bladoxy/modules/__init__.py
bladoxy/modules/dependencies_src/autoconf-latest.tar.gz
bladoxy/modules/dependencies_src/m4-latest.tar.gz
bladoxy/modules/dependencies_src/pcre-8.44.tar.gz
bladoxy/modules/dependencies_src/privoxy-3.0.34-stable-src.tar.gz
bladoxy/modules/dependencies_src/zlib-1.3.1.tar.gz
bladoxy/modules/shadowsocks_module/__init__.py
bladoxy/modules/shadowsocks_module/shadowsocks/__init__.py
bladoxy/modules/shadowsocks_module/shadowsocks/asyncdns.py
bladoxy/modules/shadowsocks_module/shadowsocks/common.py
bladoxy/modules/shadowsocks_module/shadowsocks/daemon.py
bladoxy/modules/shadowsocks_module/shadowsocks/encrypt.py
bladoxy/modules/shadowsocks_module/shadowsocks/eventloop.py
bladoxy/modules/shadowsocks_module/shadowsocks/local.py
bladoxy/modules/shadowsocks_module/shadowsocks/lru_cache.py
bladoxy/modules/shadowsocks_module/shadowsocks/manager.py
bladoxy/modules/shadowsocks_module/shadowsocks/server.py
bladoxy/modules/shadowsocks_module/shadowsocks/shell.py
bladoxy/modules/shadowsocks_module/shadowsocks/tcprelay.py
bladoxy/modules/shadowsocks_module/shadowsocks/udprelay.py
bladoxy/modules/shadowsocks_module/shadowsocks/crypto/__init__.py
bladoxy/modules/shadowsocks_module/shadowsocks/crypto/openssl.py
bladoxy/modules/shadowsocks_module/shadowsocks/crypto/rc4_md5.py
bladoxy/modules/shadowsocks_module/shadowsocks/crypto/sodium.py
bladoxy/modules/shadowsocks_module/shadowsocks/crypto/table.py
bladoxy/modules/shadowsocks_module/shadowsocks/crypto/util.py
bladoxy/utils/__init__.py
bladoxy/utils/check_availability.py
bladoxy/utils/configure_port.py
bladoxy/utils/get_available_port.py
bladoxy/utils/kill_process.py
bladoxy/utils/logger.py
bladoxy/utils/make_privoxy.py
bladoxy/utils/nodes.py
bladoxy/utils/print_info.py
bladoxy/utils/print_license.py
bladoxy/utils/set_env.py
bladoxy/utils/start_process.py
bladoxy-1.4.4.dist-info/METADATA
bladoxy-1.4.4.dist-info/WHEEL
bladoxy-1.4.4.dist-info/entry_points.txt
bladoxy-1.4.4.dist-info/top_level.txt
bladoxy-1.4.4.dist-info/RECORD
