Metadata-Version: 2.1
Name: bladoxy
Version: 1.4.4
Summary: Bladoxy is a linux network assistant.
Home-page: https://github.com/magicum-sidus/Bladoxy
Author: Magicum Sidus
Author-email: M.S@MS.com
License: http://www.apache.org/licenses/LICENSE-2.0
Classifier: License :: OSI Approved :: Apache Software License
Classifier: Programming Language :: Python :: 3
Classifier: Programming Language :: Python :: Implementation :: CPython
Classifier: Programming Language :: Python :: Implementation :: PyPy
Classifier: Topic :: Internet :: Proxy Servers
Requires-Python: >=3.5, <3.10
Requires-Dist: termcolor
Requires-Dist: pyyaml
